modson/VERSION
modson/__init__.py
modson/__main__.py
modson/runtime.py
modson-1.0.0.dist-info/licenses/LICENSE
modson-1.0.0.dist-info/METADATA
modson-1.0.0.dist-info/WHEEL
modson-1.0.0.dist-info/entry_points.txt
modson-1.0.0.dist-info/top_level.txt
modson-1.0.0.dist-info/RECORD
