Metadata-Version: 2.4
Name: modson
Version: 1.0.0
Summary: Meson wrapper to load custom modules for complex build systems
Home-page: https://github.com/alex-bouget/modson
Author: alex-bouget
Keywords: meson,build,mesonbuild,modules,wrapper,custom,modson
Classifier: Development Status :: 2 - Pre-Alpha
Classifier: Environment :: Console
Classifier: Intended Audience :: Developers
Classifier: License :: OSI Approved :: MIT License
Classifier: Programming Language :: Python :: 3 :: Only
Classifier: Topic :: Software Development :: Build Tools
License-File: LICENSE
Requires-Dist: meson>=1.0.0
Requires-Dist: colorama>=0.4.6
Dynamic: author
Dynamic: classifier
Dynamic: description
Dynamic: description-content-type
Dynamic: home-page
Dynamic: keywords
Dynamic: license-file
Dynamic: requires-dist
Dynamic: summary
